{
    "start_block": {
        "id": "09fee589937c94cac9fcd9c75b6022c5b876a34c46e858fdfb6bdd8a1b3fcd8f",
        "num": 167699849,
        "time": "2021-02-11T00:00:00Z"
    },
    "stop_block": {
        "id": "0a01886fb0814afbfac607d7a939d03e4a4f3025c5c6cc59a04524f18ce15333",
        "num": 167872623,
        "time": "2021-02-11T23:59:59Z"
    },
    "data": {
        "rex": {
            "state": {
                "rexpool": {
                    "total_lent": 32390083.7218,
                    "total_unlent": 28985509.0735,
                    "total_rent": 8255.5475,
                    "total_lendable": 61375592.7953,
                    "total_rex": 608563507676.564,
                    "namebid_proceeds": 0,
                    "loan_num": 460294
                },
                "rexretpool": {
                    "last_dist_time": "2021-02-12T09:40:00",
                    "pending_bucket_time": "2021-02-12T12:00:00",
                    "oldest_bucket_time": "2021-01-13T12:00:00",
                    "pending_bucket_proceeds": 1359230,
                    "current_rate_of_increase": 31918,
                    "proceeds": 65227930
                }
            },
            "actions": {
                "deposit": {
                    "amount": 7543040.430799748,
                    "actions": 12613
                },
                "withdraw": {
                    "amount": 29597685.456099987,
                    "actions": 7799
                },
                "buyrex": {
                    "price": 0.0001008532257046204,
                    "amount": 7546069.112099997,
                    "actions": 5507
                },
                "sellrex": {
                    "price": 0.0001008532257046204,
                    "rex": 293093064634.20087,
                    "actions": 7674
                },
                "rentcpu": {
                    "price": 3510.6088923366574,
                    "loan_payment": 10184.531700000482,
                    "loan_fund": 115.55450000000009,
                    "actions": 7625
                },
                "rentnet": {
                    "price": 3510.6088923366574,
                    "loan_payment": 228.4106,
                    "loan_fund": 8.075799999999997,
                    "actions": 1254
                },
                "unstaketorex": {
                    "from_net": 44711.248699999975,
                    "from_cpu": 283118.8637000004,
                    "actions": 611
                },
                "mvtosavings": {
                    "rex": 7390985846.715602,
                    "actions": 265
                },
                "mvfrsavings": {
                    "rex": 25252818260.74781,
                    "actions": 576
                },
                "powerup": {
                    "cpu_frac": 0,
                    "net_frac": 0,
                    "actions": 0
                },
                "powupresult": {
                    "fee": 0,
                    "powup_cpu": 0,
                    "powup_cpu_price": null,
                    "powup_net": 0,
                    "actions": 0
                }
            }
        },
        "ram": {
            "state": {
                "rammarket": {
                    "supply": 10000000000,
                    "base": 157494170525,
                    "quote": 5547981.9377
                },
                "global": {
                    "max_ram_size": 235466753024,
                    "total_ram_bytes_reserved": 77837990275,
                    "total_ram_stake": 45494968718
                }
            },
            "actions": {
                "buyram": {
                    "price_kb": 27.71962815782004,
                    "quant": 43471.45429999998,
                    "actions": 15201
                },
                "buyrambytes": {
                    "price_kb": 0.03607552,
                    "bytes": 375075643,
                    "actions": 62627
                }
            }
        },
        "cpu": {
            "actions": {
                "delegatebw": {
                    "stake_net_quantity": 10234629.108699134,
                    "stake_cpu_quantity": 11031250.546395719,
                    "actions": 95317
                },
                "undelegatebw": {
                    "unstake_net_quantity": 8472655.766496975,
                    "unstake_cpu_quantity": 16698585.297292335,
                    "actions": 75068
                }
            }
        }
    }
}