{
    "start_block": {
        "id": "0e4c8de642e2b0fbf244cbdf293b4934fe3c876f6951cddbc2a32b0cd7176b57",
        "num": 239898086,
        "time": "2022-04-05T00:00:00Z"
    },
    "stop_block": {
        "id": "0e4f30e3b7df8155002922bde248988a0ffac457c384f7523b7be53142270715",
        "num": 240070883,
        "time": "2022-04-05T23:59:59Z"
    },
    "data": {
        "rex": {
            "state": {
                "rexpool": {
                    "total_lent": 6991179.1884,
                    "total_unlent": 50392415.2044,
                    "total_rent": 3760.7997,
                    "total_lendable": 57383594.3928,
                    "total_rex": 566788564371.2343,
                    "namebid_proceeds": 0,
                    "loan_num": 498513
                },
                "rexretpool": {
                    "last_dist_time": "2022-04-05T23:50:00",
                    "pending_bucket_time": "2022-04-06T00:00:00",
                    "oldest_bucket_time": "2022-03-07T00:00:00",
                    "pending_bucket_proceeds": 1718229,
                    "current_rate_of_increase": 22419,
                    "proceeds": 49628496
                }
            },
            "actions": {
                "deposit": {
                    "amount": 22714519.138100278,
                    "actions": 17802
                },
                "withdraw": {
                    "amount": 21354624.05070008,
                    "actions": 16345
                },
                "buyrex": {
                    "price": 0.00010124338774629015,
                    "amount": 28126938.652100135,
                    "actions": 13968
                },
                "sellrex": {
                    "price": 0.00010124338774629015,
                    "rex": 265042229278.95456,
                    "actions": 16351
                },
                "rentcpu": {
                    "price": 13395.82625954274,
                    "loan_payment": 3507.688999999957,
                    "loan_fund": 158.65749999999963,
                    "actions": 3844
                },
                "rentnet": {
                    "price": 13395.82625954274,
                    "loan_payment": 406.59110000000106,
                    "loan_fund": 138.5400999999995,
                    "actions": 929
                },
                "unstaketorex": {
                    "from_net": 74105.61690000026,
                    "from_cpu": 219904.6111999998,
                    "actions": 1603
                },
                "mvtosavings": {
                    "rex": 14202434449.9811,
                    "actions": 1063
                },
                "mvfrsavings": {
                    "rex": 14465446099.473614,
                    "actions": 819
                },
                "powerup": {
                    "cpu_frac": 5782527360102480,
                    "net_frac": 106024762968525,
                    "actions": 609349
                },
                "powupresult": {
                    "fee": 1000036133.4284426,
                    "powup_cpu": 1002183290879779000,
                    "powup_cpu_price": 6534297.488235294,
                    "powup_net": 1000009983112876800,
                    "actions": 609350
                }
            }
        },
        "ram": {
            "state": {
                "rammarket": {
                    "supply": 10000000000,
                    "base": 216633818564,
                    "quote": 5996393.4621
                },
                "global": {
                    "max_ram_size": 309181238272,
                    "total_ram_bytes_reserved": 92547419708,
                    "total_ram_stake": 49963934621
                }
            },
            "actions": {
                "buyram": {
                    "price_kb": 35.280437138728324,
                    "quant": 110278.75989999402,
                    "actions": 35052
                },
                "buyrambytes": {
                    "price_kb": 0.02834432,
                    "bytes": 9046969796,
                    "actions": 2134886
                }
            }
        },
        "cpu": {
            "actions": {
                "delegatebw": {
                    "stake_net_quantity": 1540555.5354011985,
                    "stake_cpu_quantity": 14188228.109162511,
                    "actions": 414858
                },
                "undelegatebw": {
                    "unstake_net_quantity": 6222359.256695376,
                    "unstake_cpu_quantity": 11071691.445099613,
                    "actions": 46654
                }
            }
        }
    }
}